[
  {
    "featureType": "road.highway",
    "elementType": "geometry.fill",
    "stylers": [
      {
        "color": "#55a9ce"
      }
    ]
  },
  {
    "featureType": "road.highway",
    "elementType": "geometry.stroke",
    "stylers": [
      {
        "color": "#70bfe1"
      }
    ]
  },
  {
    "featureType": "road.highway.controlled_access",
    "elementType": "geometry.fill",
    "stylers": [
      {
        "color": "#7dc5e3"
      }
    ]
  },
  {
    "featureType": "water",
    "elementType": "geometry.fill",
    "stylers": [
      {
        "color": "#62d3f9"
      }
    ]
  }
]